pypredictor/__init__.py
pypredictor/_exceptions.py
pypredictor/numgraph.py
pypredictor/numpredict.py
pypredictor-0.1.1.dist-info/LICENSE
pypredictor-0.1.1.dist-info/METADATA
pypredictor-0.1.1.dist-info/WHEEL
pypredictor-0.1.1.dist-info/top_level.txt
pypredictor-0.1.1.dist-info/RECORD
