Metadata-Version: 2.1
Name: pypredictor
Version: 0.1.1
Summary: The Python library that makes AI predictions simple.
Home-page: UNKNOWN
Author: codingboy_CW (Hamd Waseem)
Author-email: codingboy.cw@gmail.com
License: Apache-2.0
Keywords: python,prediction,ai
Platform: UNKNOWN
Classifier: Development Status :: 4 - Beta
Classifier: Intended Audience :: Developers
Classifier: Programming Language :: Python :: 3
Classifier: Operating System :: Unix
Classifier: Operating System :: MacOS :: MacOS X
Classifier: Operating System :: Microsoft :: Windows
Classifier: License :: OSI Approved :: Apache Software License
License-File: LICENSE
Requires-Dist: tensorflow
Requires-Dist: pandas
Requires-Dist: numpy
Requires-Dist: matplotlib
Requires-Dist: seaborn
